tamil_utils/__init__.py
tamil_utils/cli.py
tamil_utils/core.py
tamil_utils/corpus.py
tamil_utils/hf_export.py
tamil_utils/preprocess.py
tamil_utils/spacy_hook.py
tamil_utils-0.4.0.dist-info/licenses/LICENSE
tamil_utils-0.4.0.dist-info/METADATA
tamil_utils-0.4.0.dist-info/WHEEL
tamil_utils-0.4.0.dist-info/entry_points.txt
tamil_utils-0.4.0.dist-info/top_level.txt
tamil_utils-0.4.0.dist-info/RECORD
