Metadata-Version: 2.4
Name: tamil-utils
Version: 0.4.0
Summary: Tiny Tamil text utilities: normalize, tokenize, stopwords, graphemes, n-grams, syllables, Tamil collation; dataset preprocessor; optional spaCy tokenizer hook.
Author: Arulnidhi Karunanidhi
License: MIT
Project-URL: Homepage, https://github.com/arulnidhii/tamil-utils
Project-URL: Documentation, https://arulnidhii.github.io/tamil-utils/
Project-URL: Source, https://github.com/arulnidhii/tamil-utils
Project-URL: Issues, https://github.com/arulnidhii/tamil-utils/issues
Keywords: tamil,indic,nlp,unicode,rag,spacy,tokenization
Classifier: Programming Language :: Python :: 3
Classifier: License :: OSI Approved :: MIT License
Classifier: Operating System :: OS Independent
Classifier: Topic :: Text Processing :: Linguistic
Classifier: Intended Audience :: Developers
Classifier: Typing :: Typed
Requires-Python: >=3.9
License-File: LICENSE
Requires-Dist: regex>=2023.0
Provides-Extra: spacy
Requires-Dist: spacy<4,>=3.6; extra == "spacy"
Provides-Extra: hf
Requires-Dist: datasets>=2.16.0; extra == "hf"
Provides-Extra: dev
Requires-Dist: pytest>=7; extra == "dev"
Requires-Dist: pytest-benchmark>=4; extra == "dev"
Requires-Dist: mkdocs>=1.5; extra == "dev"
Requires-Dist: mkdocs-material>=9; extra == "dev"
Dynamic: license-file
